{
  "name": "marcs-gale-hub",
  "version": "1.0.0",
  "description": "Personalized business intelligence dashboard for marketing agency clients",
  "main": "index.js",
  "scripts": {
    "dev": "node server.js",
    "build": "echo 'Build complete'",
    "start": "node server.js"
  },
  "keywords": ["dashboard", "news", "intelligence"],
  "author": "Marc Parillo",
  "license": "MIT",
  "dependencies": {
    "express": "^4.18.2",
    "cors": "^2.8.5",
    "dotenv": "^16.3.1",
    "axios": "^1.6.2",
    "node-cron": "^3.0.2",
    "rss-parser": "^3.13.0"
  }
}
